{"buildtools_1-devenv.md":"_H8Na_BW","buildtools_2-command.md":"QTdA6V2K","buildtools_3-structure.md":"pAGKqTrx","buildtools_4-resolution.md":"BFhItFtD","buildtools_5-builders_1-modules.md":"B4nbi3lu","buildtools_5-builders_2-docs.md":"CmxMNayE","buildtools_5-builders_3-manifest.md":"QtKuJkHi","buildtools_5-builders_index.md":"7pl9ZjHU","buildtools_6-prebuild.md":"BK3AiGEg","buildtools_7-templates.md":"DeLpVjFb","buildtools_8-testing.md":"Do8UBZOz","buildtools_index.md":"Dte9tUpN","index.md":"DDRloB8H","lib_dev_curve.md":"DWcT2qli","lib_dev_game.md":"Chj0z3-T","lib_dev_index.md":"BcC5SYaG","lib_index.md":"DhzRc12x","lib_lintplugin_1-overview.md":"D3EExktz","lib_lintplugin_2-rules.md":"D8uX-iiv","lib_lintplugin_3-config.md":"DcrA-YaH","lib_lintplugin_index.md":"CJWnI2Dn","lib_modules-lib_index.md":"DlLiS4xi","lib_modules-lib_specialerrors.md":"D1l5ATeh","lib_modules-lib_tabs.md":"DovEg0se","lib_modules-lib_type-maps.md":"CvlrC_f2","lib_modules-lib_types.md":"uV6RP86-","lib_modules-lib_utilities.md":"CMuxa1N2","modules_1-getting-started_1-overview.md":"6AQmn6we","modules_1-getting-started_2-start.md":"Dcj8mbAC","modules_1-getting-started_3-git.md":"EvP2NGrO","modules_1-getting-started_4-cheat.md":"BdatWHst","modules_1-getting-started_5-faq.md":"CHlNyILm","modules_1-getting-started_6-troubleshooting.md":"BtE75Kv4","modules_1-getting-started_index.md":"D5Utv2ht","modules_2-bundle_1-overview_1-overview.md":"BxabiqvM","modules_2-bundle_2-creating_2-creating.md":"Cbi7dd_1","modules_2-bundle_3-editing.md":"CCFU2gOJ","modules_2-bundle_4-conventions_1-basic.md":"i7wtN435","modules_2-bundle_4-conventions_2-abstractions.md":"C-QQTu0h","modules_2-bundle_4-conventions_3-errors.md":"CI6nIjK3","modules_2-bundle_4-conventions_index.md":"DvhIUGAq","modules_2-bundle_5-documentation_1-cadet_1-cadet.md":"mxnhv3Om","modules_2-bundle_5-documentation_2-dev.md":"DpPpQCaN","modules_2-bundle_5-documentation_index.md":"CSz846Wu","modules_2-bundle_6-compiling.md":"CYrmJCoT","modules_2-bundle_7-type_map.md":"47IiNlMZ","modules_2-bundle_index.md":"CCbuUV37","modules_3-tabs_1-overview.md":"DGnnrrO4","modules_3-tabs_2-creating.md":"D6hBTis-","modules_3-tabs_3-editing.md":"CIveq4uh","modules_3-tabs_4-context_4-context.md":"DOBhTRV0","modules_3-tabs_5-compiling.md":"CLpkYJQH","modules_3-tabs_index.md":"CGDKd-HK","modules_4-testing_1-desktop.md":"BJWpfPnh","modules_4-testing_2-devserver_2-devserver.md":"C_khbFN-","modules_4-testing_3-frontend.md":"DGROWetc","modules_4-testing_4-unit_1-general.md":"CLN9nNxA","modules_4-testing_4-unit_2-unit.md":"7oiHoHPM","modules_4-testing_4-unit_3-browser.md":"cGVxfUZz","modules_4-testing_4-unit_index.md":"xZoMhGZg","modules_4-testing_index.md":"DUoPP9-W","modules_5-advanced_context.md":"CUGi7NJ5","modules_5-advanced_cross-use.md":"DHi1qOWS","modules_5-advanced_flow_flow.md":"CWcbYgxl","modules_5-advanced_index.md":"BG5QaNYf","modules_5-advanced_linting.md":"B10oK_ko","modules_5-advanced_manifest.md":"Cas5rdhp","modules_5-advanced_misc.md":"C5D64RYB","modules_5-advanced_typescript.md":"DwNU60zy","modules_index.md":"CZAkkltB","repotools_1-devserver.md":"DSGPvl1t","repotools_2-linting.md":"_UpYXT6W","repotools_3-reporters.md":"W69xHiyb","repotools_4-vscode.md":"RQsDjsdG","repotools_5-yarn.md":"DCWzsZJt","repotools_6-docserver_1-overview.md":"_ARYy2q5","repotools_6-docserver_2-dirtree.md":"eC5Fclw_","repotools_6-docserver_3-spellcheck.md":"Li65iVPF","repotools_6-docserver_index.md":"DJ4OsxHW","repotools_7-workflows_1-actions.md":"BFAyxeyL","repotools_7-workflows_2-pull-request.md":"CN-fSpkE","repotools_7-workflows_3-workflows.md":"C4DfxYnz","repotools_7-workflows_index.md":"DI56Fmpk","repotools_index.md":"BHwGtcId"}
