{"buildtools_1-devenv.md":"GDwN2ALd","buildtools_2-command.md":"CYpsXJEw","buildtools_3-structure.md":"CD-oV3L6","buildtools_4-resolution.md":"C-6ZsL7T","buildtools_5-builders_1-modules.md":"CvRXrPVC","buildtools_5-builders_2-docs.md":"BRrh_U0e","buildtools_5-builders_3-manifest.md":"C-AmdtZX","buildtools_5-builders_index.md":"uj9aqMM9","buildtools_6-prebuild.md":"GVZ51Niq","buildtools_7-templates.md":"BxvLQM6q","buildtools_8-testing.md":"gOpICCf5","buildtools_index.md":"BpPt0HHr","index.md":"B3Az3V9i","lib_dev_curve.md":"GtL30JKq","lib_dev_game.md":"CG29b3me","lib_dev_index.md":"Wbg-7SVa","lib_index.md":"-RYeYojV","lib_lintplugin_1-overview.md":"46nuWj-U","lib_lintplugin_2-rules_2-rules.md":"xmjQ_DQn","lib_lintplugin_2-rules_default-import-name.md":"CvMrHooD","lib_lintplugin_2-rules_instanceof-check.md":"CDXJeet7","lib_lintplugin_2-rules_no-barrel-imports.md":"e9ilyrYp","lib_lintplugin_2-rules_region-comment.md":"uK4PQueb","lib_lintplugin_2-rules_tab-type.md":"BVjPTNvC","lib_lintplugin_2-rules_throw-runtime-error.md":"Bcj1Z0N0","lib_lintplugin_3-config.md":"CqqeEm82","lib_lintplugin_index.md":"b_cumPEz","lib_modules-lib_errors.md":"BPGoIU-u","lib_modules-lib_index.md":"CdRKlBnN","lib_modules-lib_specialerrors.md":"DUEmkrJC","lib_modules-lib_tabs.md":"CqL4ModG","lib_modules-lib_type-maps.md":"D6pvtiM8","lib_modules-lib_types.md":"Qov_Zcgn","lib_modules-lib_utilities.md":"CBK5-TH0","modules_1-getting-started_1-overview.md":"BLejQB8h","modules_1-getting-started_2-start.md":"BF9AeXKw","modules_1-getting-started_3-git.md":"Ltd_JuMz","modules_1-getting-started_4-typescript_4-typescript.md":"BG95OA99","modules_1-getting-started_5-cheat.md":"C8TTao7Q","modules_1-getting-started_6-faq.md":"RcHslsai","modules_1-getting-started_7-troubleshooting.md":"CBkQFrpI","modules_1-getting-started_index.md":"D0ajHWK2","modules_2-bundle_1-overview_1-overview.md":"h7uA5Iz2","modules_2-bundle_2-creating_2-creating.md":"CoMWgn9q","modules_2-bundle_3-editing.md":"tsTAnsMk","modules_2-bundle_4-conventions_1-basic.md":"U7uZ076o","modules_2-bundle_4-conventions_2-abstractions.md":"BHHsQ_L7","modules_2-bundle_4-conventions_3-errors.md":"SLgqEbMp","modules_2-bundle_4-conventions_4-types.md":"C8HZ_gzA","modules_2-bundle_4-conventions_index.md":"CCfz-9DH","modules_2-bundle_5-documentation_1-cadet_1-cadet.md":"Bs1D_MzQ","modules_2-bundle_5-documentation_2-dev.md":"Db1NzupZ","modules_2-bundle_5-documentation_index.md":"BhUbfQAR","modules_2-bundle_6-compiling.md":"fQnUinyX","modules_2-bundle_7-type_map.md":"CUXT2bK3","modules_2-bundle_index.md":"kBBsQwhP","modules_3-tabs_1-overview.md":"CdhfruK1","modules_3-tabs_2-creating.md":"BY5XG3Ob","modules_3-tabs_3-editing.md":"CgPb9rko","modules_3-tabs_4-compiling.md":"Cmu6dte3","modules_3-tabs_5-animations_5-animations.md":"PIlEblWQ","modules_3-tabs_index.md":"kgIWuiC4","modules_4-testing_1-desktop.md":"DDtbV7_l","modules_4-testing_2-devserver_2-devserver.md":"BK7jYDhW","modules_4-testing_3-frontend.md":"DJ2RKBi2","modules_4-testing_4-unit_1-general.md":"DEA14J6a","modules_4-testing_4-unit_2-unit.md":"mKOHzSex","modules_4-testing_4-unit_3-mock.md":"rnK7A8NA","modules_4-testing_4-unit_4-browser.md":"D39j-XSJ","modules_4-testing_4-unit_index.md":"Ds4wulFk","modules_4-testing_index.md":"BE2I5-mA","modules_5-advanced_context.md":"2XCh82Q0","modules_5-advanced_flow_flow.md":"D24CG2zJ","modules_5-advanced_index.md":"BExJ1QdI","modules_5-advanced_linting.md":"CR1lkIhT","modules_5-advanced_manifest.md":"CZUPhZpO","modules_5-advanced_misc.md":"B2nK9x75","modules_index.md":"D49RqyqN","repotools_1-devserver.md":"CEJWQjJz","repotools_2-linting.md":"Cf93ZkCQ","repotools_3-reporters.md":"D20R6ftW","repotools_4-vscode.md":"DmtfhrUr","repotools_5-yarn.md":"DOK6hUgr","repotools_6-docserver_1-overview.md":"DcwfJOcY","repotools_6-docserver_2-dirtree.md":"CmTCnReL","repotools_6-docserver_3-spellcheck.md":"DTe9pkts","repotools_6-docserver_4-twoslash.md":"CYx5Pidl","repotools_6-docserver_index.md":"DYvBf6ce","repotools_7-workflows_1-actions.md":"B1WLSZ6q","repotools_7-workflows_2-pull-request.md":"CXttsJd-","repotools_7-workflows_3-workflows.md":"V1dJ9g6u","repotools_7-workflows_4-changes.md":"Utf0mJ7S","repotools_7-workflows_index.md":"DDqezFJf","repotools_index.md":"W9G-gc7Q"}
