{"buildtools_1-devenv.md":"BgnbANGm","buildtools_2-command.md":"s5wDFxQX","buildtools_3-structure.md":"BllyracM","buildtools_4-resolution.md":"XvnXEx1K","buildtools_5-builders_1-modules.md":"CHc0rjkB","buildtools_5-builders_2-docs.md":"rY8wOsIZ","buildtools_5-builders_3-manifest.md":"BsVhC6Go","buildtools_5-builders_index.md":"v_LBIOjA","buildtools_6-prebuild.md":"CxCb6vf8","buildtools_7-templates.md":"CH9a_MZV","buildtools_8-testing.md":"piXRQ3VC","buildtools_index.md":"CtL51oTm","index.md":"_wYr26_C","lib_dev_curve.md":"cXghTef6","lib_dev_game.md":"BRW34oN_","lib_dev_index.md":"CUg3FKS0","lib_index.md":"Ddav7hO7","lib_lintplugin_1-overview.md":"DRzweUQD","lib_lintplugin_2-rules.md":"BjJF49TK","lib_lintplugin_3-config.md":"Cjn2S1cE","lib_lintplugin_index.md":"Bz0VpnMg","lib_modules-lib_index.md":"CE4atfsA","lib_modules-lib_specialerrors.md":"kojqR2tk","lib_modules-lib_tabs.md":"B0p5BqXS","lib_modules-lib_type-maps.md":"R__glljW","lib_modules-lib_types.md":"5NKFhaIC","lib_modules-lib_utilities.md":"bBlPqPnh","modules_1-getting-started_1-overview.md":"DQt_TvaN","modules_1-getting-started_2-start.md":"DUvpOTNW","modules_1-getting-started_3-git.md":"DRf2Z0Xt","modules_1-getting-started_4-cheat.md":"CMrHZLT5","modules_1-getting-started_5-faq.md":"DTKHiuzm","modules_1-getting-started_6-troubleshooting.md":"iWHKoDgg","modules_1-getting-started_index.md":"DtCqI1K2","modules_2-bundle_1-overview_1-overview.md":"Bs7YgGZt","modules_2-bundle_2-creating_2-creating.md":"Bc5lfHal","modules_2-bundle_3-editing.md":"DzJ0ERwb","modules_2-bundle_4-conventions_1-basic.md":"DKer7ipg","modules_2-bundle_4-conventions_2-abstractions.md":"BjfS60Qk","modules_2-bundle_4-conventions_3-errors.md":"BJO45xoL","modules_2-bundle_4-conventions_4-types.md":"HEC4mB_6","modules_2-bundle_4-conventions_index.md":"Cbrv_YTU","modules_2-bundle_5-documentation_1-cadet_1-cadet.md":"C47FoUxJ","modules_2-bundle_5-documentation_2-dev.md":"vGqVb18T","modules_2-bundle_5-documentation_index.md":"CGLA_JsD","modules_2-bundle_6-compiling.md":"DncDQnhB","modules_2-bundle_7-type_map.md":"DhhiBe9h","modules_2-bundle_index.md":"BsCu7NGF","modules_3-tabs_1-overview.md":"Bqhamx-q","modules_3-tabs_2-creating.md":"BcLbqjpv","modules_3-tabs_3-editing.md":"3Q4fp15O","modules_3-tabs_4-compiling.md":"CtWe4dLr","modules_3-tabs_index.md":"gtVbxMgw","modules_4-testing_1-desktop.md":"BwfsVqdF","modules_4-testing_2-devserver_2-devserver.md":"BhYXw0Kt","modules_4-testing_3-frontend.md":"BiTIzAdI","modules_4-testing_4-unit_1-general.md":"DA4cE0Dj","modules_4-testing_4-unit_2-unit.md":"BZWgLaGo","modules_4-testing_4-unit_3-mock.md":"BxtsCIHp","modules_4-testing_4-unit_4-browser.md":"Bz9FULRn","modules_4-testing_4-unit_index.md":"BHf63OAH","modules_4-testing_index.md":"B2flK9RX","modules_5-advanced_context.md":"CAGgLvCw","modules_5-advanced_cross-use.md":"BcIcC4ct","modules_5-advanced_flow_flow.md":"lNB7smTW","modules_5-advanced_index.md":"CfFsn2XN","modules_5-advanced_linting.md":"CG0FJLxN","modules_5-advanced_manifest.md":"DnUNP5Uc","modules_5-advanced_misc.md":"Ca9pbnd5","modules_5-advanced_typescript.md":"CbVXV5A3","modules_index.md":"DSKOTJD1","repotools_1-devserver.md":"4lJFCmLx","repotools_2-linting.md":"CByHgDjt","repotools_3-reporters.md":"C3k27uSO","repotools_4-vscode.md":"B1lGGdGv","repotools_5-yarn.md":"BhDa_iCd","repotools_6-docserver_1-overview.md":"Dmt75qFU","repotools_6-docserver_2-dirtree.md":"B59rIiaH","repotools_6-docserver_3-spellcheck.md":"BnjDvwzj","repotools_6-docserver_index.md":"CCC5F6yK","repotools_7-workflows_1-actions.md":"DFMsvbhz","repotools_7-workflows_2-pull-request.md":"BA8zW7Hg","repotools_7-workflows_3-workflows.md":"CnkRRhXi","repotools_7-workflows_4-changes.md":"BbXRUxuO","repotools_7-workflows_index.md":"BeFpoRzq","repotools_index.md":"CWPfg89C"}
