{"buildtools_1-devenv.md":"DRIUP273","buildtools_2-command.md":"ZSlYHyUo","buildtools_3-structure.md":"Dtti0364","buildtools_4-resolution.md":"DZDe_1vx","buildtools_5-builders_1-modules.md":"BkiD-cDP","buildtools_5-builders_2-docs.md":"ByPjEhWl","buildtools_5-builders_3-manifest.md":"DAtc9UNg","buildtools_5-builders_index.md":"DvYz_uSq","buildtools_6-prebuild.md":"B5L7iL-f","buildtools_7-templates.md":"PfpF3Dcn","buildtools_8-testing.md":"DHXakNXC","buildtools_index.md":"CJBRQuD4","index.md":"hK5dyhMH","lib_dev_curve.md":"DsRoirQY","lib_dev_game.md":"DQQa1AG9","lib_dev_index.md":"Cjtfo2E_","lib_index.md":"weOCDlvU","lib_lintplugin_1-overview.md":"CQdbIGHk","lib_lintplugin_2-rules_2-rules.md":"Ca9yD4HC","lib_lintplugin_2-rules_default-import-name.md":"oclu6cma","lib_lintplugin_2-rules_instanceof-check.md":"B5oTzwKF","lib_lintplugin_2-rules_no-barrel-imports.md":"CXHixaGA","lib_lintplugin_2-rules_region-comment.md":"CRkHOs8U","lib_lintplugin_2-rules_tab-type.md":"CzgoR-9j","lib_lintplugin_2-rules_throw-runtime-error.md":"Cf_bW1xk","lib_lintplugin_3-config.md":"DBJZQ1dB","lib_lintplugin_index.md":"_ha4bppN","lib_modules-lib_errors.md":"BPGoIU-u","lib_modules-lib_index.md":"CdRKlBnN","lib_modules-lib_specialerrors.md":"CjOIBAxH","lib_modules-lib_tabs.md":"CyKrA-_t","lib_modules-lib_type-maps.md":"BdeTYGQ8","lib_modules-lib_types.md":"Gu6sbLa0","lib_modules-lib_utilities.md":"cUPspayK","modules_1-getting-started_1-overview.md":"CdQRV3ad","modules_1-getting-started_2-start.md":"C1cD7Zc8","modules_1-getting-started_3-git.md":"a_M2nnle","modules_1-getting-started_4-typescript_4-typescript.md":"D8szMaZJ","modules_1-getting-started_5-cheat.md":"BSvWL7sc","modules_1-getting-started_6-faq.md":"qh8eGj1S","modules_1-getting-started_7-troubleshooting.md":"Bt70d_Hx","modules_1-getting-started_index.md":"BTGkn7WN","modules_2-bundle_1-overview_1-overview.md":"CZgpoGJG","modules_2-bundle_2-creating_2-creating.md":"CADzA__s","modules_2-bundle_3-editing.md":"BGLD_xou","modules_2-bundle_4-conventions_1-basic.md":"LFKXKYQ4","modules_2-bundle_4-conventions_2-abstractions.md":"BPuwpv_S","modules_2-bundle_4-conventions_3-errors.md":"9b7NSe42","modules_2-bundle_4-conventions_4-types.md":"BQGFWyUV","modules_2-bundle_4-conventions_index.md":"BFoTCJyA","modules_2-bundle_5-documentation_1-cadet_1-cadet.md":"Big9MnMP","modules_2-bundle_5-documentation_2-dev.md":"D1tXNXxM","modules_2-bundle_5-documentation_index.md":"C07yxeSP","modules_2-bundle_6-compiling.md":"DzLPM5-G","modules_2-bundle_7-type_map.md":"C-AXIatH","modules_2-bundle_index.md":"DSgKp_ts","modules_3-tabs_1-overview.md":"BNSqBT6h","modules_3-tabs_2-creating.md":"DP87k2Zw","modules_3-tabs_3-editing.md":"DFgJQTe5","modules_3-tabs_4-compiling.md":"CWfReQ0b","modules_3-tabs_5-animations_5-animations.md":"BhR4OfFV","modules_3-tabs_index.md":"Dsfbtdij","modules_4-testing_1-desktop.md":"BL5Ktjuv","modules_4-testing_2-devserver_2-devserver.md":"V0kfYzw6","modules_4-testing_3-frontend.md":"kzUSJYKI","modules_4-testing_4-unit_1-general.md":"jSt2DJkf","modules_4-testing_4-unit_2-unit.md":"BI9GAuv3","modules_4-testing_4-unit_3-mock.md":"DviBUuqh","modules_4-testing_4-unit_4-browser.md":"uBhs3imn","modules_4-testing_4-unit_index.md":"KuqxF4tZ","modules_4-testing_index.md":"BHsN9V3z","modules_5-advanced_context.md":"BsD9f4_u","modules_5-advanced_flow_flow.md":"DUPV08VL","modules_5-advanced_index.md":"DbIhjwl6","modules_5-advanced_linting.md":"BA-Zxv7H","modules_5-advanced_manifest.md":"vRHzyD5o","modules_5-advanced_misc.md":"DFzop9Am","modules_index.md":"BD3lkda1","repotools_1-devserver.md":"BZItQ8pb","repotools_2-linting.md":"Bn65gthU","repotools_3-reporters.md":"k5CZc-zv","repotools_4-vscode.md":"BoW_TNfe","repotools_5-yarn.md":"DWrVuzH1","repotools_6-docserver_1-overview.md":"DaDmYH4W","repotools_6-docserver_2-dirtree.md":"BZTpILC0","repotools_6-docserver_3-spellcheck.md":"DVhehEC7","repotools_6-docserver_4-twoslash.md":"CQPLbnhj","repotools_6-docserver_index.md":"cT6Vj0-d","repotools_7-workflows_1-actions.md":"DmmT-uGQ","repotools_7-workflows_2-pull-request.md":"DxliRQrT","repotools_7-workflows_3-workflows.md":"B4KVrisn","repotools_7-workflows_4-changes.md":"BKbooTX0","repotools_7-workflows_index.md":"CLB9En4j","repotools_index.md":"B2JvmJFU"}
