{"buildtools_1-devenv.md":"B9Cfs-oQ","buildtools_2-command.md":"DJQHLiHV","buildtools_3-structure.md":"eKCRvsQw","buildtools_4-resolution.md":"DSq70gtw","buildtools_5-builders_1-modules.md":"B5qKojnx","buildtools_5-builders_2-docs.md":"C-emwUl9","buildtools_5-builders_3-manifest.md":"1o5o4TE5","buildtools_5-builders_index.md":"D9SdPXGP","buildtools_6-prebuild.md":"BilqpyjI","buildtools_7-templates.md":"DBsqGy81","buildtools_8-testing.md":"DcXtxO9j","buildtools_index.md":"C6sBzy70","index.md":"DA_i0i5R","lib_dev_curve.md":"DtnCLs9A","lib_dev_game.md":"BMK0Qjh3","lib_dev_index.md":"ByLsTZAK","lib_index.md":"CjXOClJu","lib_lintplugin_1-overview.md":"B8uQriWf","lib_lintplugin_2-rules.md":"Bo7gRS3-","lib_lintplugin_3-config.md":"xfCg0PoN","lib_lintplugin_index.md":"DwacGcQl","lib_modules-lib_index.md":"DlLiS4xi","lib_modules-lib_specialerrors.md":"DxabWc9p","lib_modules-lib_tabs.md":"B2K5DTQp","lib_modules-lib_type-maps.md":"CAEZvkw-","lib_modules-lib_types.md":"B_4L3s7u","lib_modules-lib_utilities.md":"D2XKXCZP","modules_1-getting-started_1-overview.md":"CY7bENzy","modules_1-getting-started_2-start.md":"B1MSfmcN","modules_1-getting-started_3-git.md":"Bd6rgdkk","modules_1-getting-started_4-cheat.md":"UiDHYdZX","modules_1-getting-started_5-faq.md":"CqOQkdO8","modules_1-getting-started_6-troubleshooting.md":"8IcvRBJ7","modules_1-getting-started_index.md":"Bhk2dbPB","modules_2-bundle_1-overview_1-overview.md":"H38L8O1D","modules_2-bundle_2-creating_2-creating.md":"Bm3CsXev","modules_2-bundle_3-editing.md":"C2bQdwo4","modules_2-bundle_4-conventions_1-basic.md":"BGhXGS8f","modules_2-bundle_4-conventions_2-abstractions.md":"CpgZuHEn","modules_2-bundle_4-conventions_3-errors.md":"DEYfGo4i","modules_2-bundle_4-conventions_index.md":"A70gfPjX","modules_2-bundle_5-documentation_1-cadet_1-cadet.md":"2ZjfCkXC","modules_2-bundle_5-documentation_2-dev.md":"CZZ70QAv","modules_2-bundle_5-documentation_index.md":"CSQfdGDP","modules_2-bundle_6-compiling.md":"CRfWO0p3","modules_2-bundle_7-type_map.md":"D9KljD6Z","modules_2-bundle_index.md":"BOfgsyyH","modules_3-tabs_1-overview.md":"DBpSVdeC","modules_3-tabs_2-creating.md":"yAIxByTA","modules_3-tabs_3-editing.md":"DApactB3","modules_3-tabs_4-compiling.md":"B43q4pvn","modules_3-tabs_index.md":"uX53GIZW","modules_4-testing_1-desktop.md":"Dr_ucpsm","modules_4-testing_2-devserver_2-devserver.md":"CpjXPgoE","modules_4-testing_3-frontend.md":"B-7JQD7y","modules_4-testing_4-unit_1-general.md":"BF6k7gHI","modules_4-testing_4-unit_2-unit.md":"BveP7yQp","modules_4-testing_4-unit_3-mock.md":"DumSj9DA","modules_4-testing_4-unit_4-browser.md":"BJe5011K","modules_4-testing_4-unit_index.md":"BcPDjFT-","modules_4-testing_index.md":"CR4ktIgZ","modules_5-advanced_context.md":"OU3pOc-8","modules_5-advanced_cross-use.md":"j-_H0iXl","modules_5-advanced_flow_flow.md":"Cri_IroU","modules_5-advanced_index.md":"Ciair6ID","modules_5-advanced_linting.md":"l2NOgPEa","modules_5-advanced_manifest.md":"BRswDEZZ","modules_5-advanced_misc.md":"B2H4EFbi","modules_5-advanced_typescript.md":"BhWK99sv","modules_index.md":"DwfvHRpo","repotools_1-devserver.md":"DjY3xuiY","repotools_2-linting.md":"B2ZYRlk4","repotools_3-reporters.md":"BKgD3L7Q","repotools_4-vscode.md":"CVnbHU0Z","repotools_5-yarn.md":"-kfCs7UA","repotools_6-docserver_1-overview.md":"Z8vVraZe","repotools_6-docserver_2-dirtree.md":"CJxz3sfV","repotools_6-docserver_3-spellcheck.md":"CVirqzWO","repotools_6-docserver_index.md":"5-TKHhoM","repotools_7-workflows_1-actions.md":"Bx7hIIXw","repotools_7-workflows_2-pull-request.md":"Dde5-TO1","repotools_7-workflows_3-workflows.md":"Bmug9DrS","repotools_7-workflows_index.md":"B6Gj7BK5","repotools_index.md":"CvT5v_uP"}
